checkContaminants/__init__.py
checkContaminants/checkContaminants.py
checkContaminants/data/curated_species.csv
checkContaminants/data/sample-infile.csv
checkContaminants/data/sample_data.csv
checkContaminants/data/score_weights.txt
checkContaminants/test/__init__.py
checkContaminants/test/test_checkContaminants.py
checkContaminants/test/data/curated_species.csv
checkContaminants/test/data/score_weights.txt
checkContaminants/test/data/gentests/fraction.csv
checkContaminants/test/data/gentests/maxcols.csv
checkContaminants/test/data/gentests/noheader.csv
checkContaminants/test/data/gentests/nonnumeric.csv
checkContaminants/test/data/gentests/repeatedcol.csv
checkContaminants/test/data/gentests/repeatedspecies.csv
checkContaminants/test/data/gentests/scinotation.csv
checkContaminants/test/data/gentests/wrongseparator.csv
checkContaminants-0.99.5.dist-info/LICENSE
checkContaminants-0.99.5.dist-info/METADATA
checkContaminants-0.99.5.dist-info/WHEEL
checkContaminants-0.99.5.dist-info/entry_points.txt
checkContaminants-0.99.5.dist-info/top_level.txt
checkContaminants-0.99.5.dist-info/RECORD
