Metadata-Version: 2.1
Name: checkContaminants
Version: 0.99.5
Summary: Command Line Package that can be used to analyse locations datasets
Home-page: https://github.com/checkContaminants/checkSpaceContamination.git
Author: Nishka Arora, Dr. Ashish Mahabal, Dr. Nitin Singh, Dr. Moogega Cooper
Author-email: naarora@caltech.edu, aam@astro.caltech.edu, nitin.k.singh@jpl.nasa.gov, moogega.cooper@jpl.nasa.gov
Project-URL: Project URL, https://github.com/checkContaminants/checkSpaceContamination
Classifier: Programming Language :: Python :: 3
Classifier: License :: OSI Approved :: MIT License
Classifier: Operating System :: OS Independent
Requires-Python: >=3.6
License-File: LICENSE
Requires-Dist: pandas (==1.3.4)
Requires-Dist: numpy (==1.22)
Requires-Dist: tabulate (==0.8.9)
Requires-Dist: matplotlib (==3.4.3)
Requires-Dist: matplotlib-venn (==0.11.6)
